main.py
cgiteste/__init__.py
cgiteste.egg-info/PKG-INFO
cgiteste.egg-info/SOURCES.txt
cgiteste.egg-info/dependency_links.txt
cgiteste.egg-info/requires.txt
cgiteste.egg-info/top_level.txt