Metadata-Version: 2.1
Name: cgiteste
Version: 0
Summary: Derivada para uso em conversões de python para o RMS
Author: CGI
Author-email: andre.ershov@cgi.com
